[{"id":"r1","name":"Carolina","address":"along beach mkpo juction","cuisine":"Nigerian","website":"https://www,carolina.com","description":"the best of all"},{"id":"r2","name":"lavila","address":"Off unn Odim gate","cuisine":"Obukpa","website":"https://www,lavila.com","description":"Run for your lifeooooo"},{"id":"r3","name":"Bonquet","address":"ejuona junction","cuisine":"Obukpa","website":"https://www,lbonque.com","description":"ehjkjhdsklkhgd"},{"id":"r4","name":"Go well","address":"ejuona junction","cuisine":"Obukpa","website":"https://www,lavila.com","description":"Specialist in puck meat"},{"name":"11:45 restuarant ","address":"behind sub UNN ","cuisine":"Aribo and Stew","website":"https://www,lbonque.com","description":"A best place to chill and enjoj","id":"04e1354e-544d-44ef-81a1-9ac891b80159"},{"name":"heath and fitnee","address":"ejuona junction","cuisine":"Nigerian","website":"https://www,carolina.com","description":"lmly7rfy","id":"3874c5d4-bb39-496a-99ee-21792850be3e"},{"name":"CHIDERA BEST DISHES","address":"FRANCO HOSTEL UNN","cuisine":"ALL TYPES OF DISHES TO YOU TASTE","website":"https://www.chidera.com","description":"Your taste is our concern ","id":"de071564-76ee-4053-a9b7-dea9488c4105"}]